setup.py
SimpleFramework.egg-info/PKG-INFO
SimpleFramework.egg-info/SOURCES.txt
SimpleFramework.egg-info/dependency_links.txt
SimpleFramework.egg-info/top_level.txt
framework/__init__.py
framework/application.py
framework/config.py
framework/request.py
framework/response.py
framework/router.py
framework/session.py
framework/sessionrepository.py
framework/state.py
framework/statichandler.py
framework/constants/__init__.py
framework/constants/httpmethods.py
framework/constants/httpstatusforcode.py
framework/email/__init__.py
framework/email/emailmessage.py
framework/email/emailsender.py
framework/httpexceptions/__init__.py
framework/httpexceptions/httpbadrequestexception.py
framework/httpexceptions/httpexception.py
framework/httpexceptions/httpnotfoundexception.py
framework/httpexceptions/httpunauthorizedexception.py
framework/util/__init__.py
framework/util/acceptcontainer.py
framework/util/cookiedict.py
framework/util/multidict.py