Metadata-Version: 1.0
Name: SimpleFramework
Version: 1.2.5
Summary: Simple Web Framework by Simplendi
Home-page: https://github.com/Simplendi/SimpleFramework
Author: Simplendi
Author-email: info@simplendi.com
License: UNKNOWN
Platform: UNKNOWN
